{
  "id": "343518ce-3ed2-41eb-a096-0206a64c933b",
  "uid": "quis-et-libero",
  "type": "posts",
  "data": {
    "title": "exploit extensible interfaces",
    "subtitle": "syndicate frictionless solutions",
    "author": "revolutionize one-to-one partnerships",
    "banner": {
      "dimensions": {
        "width": 900,
        "height": 500
      },
      "alt": "Placeholder image",
      "copyright": null,
      "url": "https://images.unsplash.com/photo-1496181133206-80ce9b88a853?w=900&h=500&fit=crop"
    }
  }
}